open_helpdesk-0.4.4.dist-info/DESCRIPTION.rst
open_helpdesk-0.4.4.dist-info/METADATA
open_helpdesk-0.4.4.dist-info/metadata.json
open_helpdesk-0.4.4.dist-info/RECORD
open_helpdesk-0.4.4.dist-info/top_level.txt
open_helpdesk-0.4.4.dist-info/WHEEL
openhelpdesk/__init__.py
openhelpdesk/admin.py
openhelpdesk/autocomplete_light_registry.py
openhelpdesk/core.py
openhelpdesk/defaults.py
openhelpdesk/forms.py
openhelpdesk/models.py
openhelpdesk/views.py
openhelpdesk/locale/en/LC_MESSAGES/django.mo
openhelpdesk/locale/en/LC_MESSAGES/django.po
openhelpdesk/locale/it/LC_MESSAGES/django.mo
openhelpdesk/locale/it/LC_MESSAGES/django.po
openhelpdesk/management/__init__.py
openhelpdesk/management/commands/__init__.py
openhelpdesk/management/commands/demohelpdesk.py
openhelpdesk/management/commands/inithelpdesk.py
openhelpdesk/migrations/0001_initial.py
openhelpdesk/migrations/0002_auto__add_source__add_pendingrange__add_activity__add_attachment__add_.py
openhelpdesk/migrations/0003_auto__add_siteconfiguration__chg_field_ticket_content.py
openhelpdesk/migrations/__init__.py
openhelpdesk/static/openhelpdesk/css/openhelpdesk.css
openhelpdesk/static/openhelpdesk/css/admin/ticket/change_form.css
openhelpdesk/static/openhelpdesk/css/jquery-ui/jquery-ui.css
openhelpdesk/static/openhelpdesk/css/jquery-ui/jquery-ui.min.css
openhelpdesk/static/openhelpdesk/css/jquery-ui/jquery-ui.structure.css
openhelpdesk/static/openhelpdesk/css/jquery-ui/jquery-ui.structure.min.css
openhelpdesk/static/openhelpdesk/css/jquery-ui/jquery-ui.theme.min.css
openhelpdesk/static/openhelpdesk/css/jquery-ui/images/animated-overlay.gif
openhelpdesk/static/openhelpdesk/css/jquery-ui/images/ui-bg_flat_0_aaaaaa_40x100.png
openhelpdesk/static/openhelpdesk/css/jquery-ui/images/ui-bg_flat_55_fffba0_40x100.png
openhelpdesk/static/openhelpdesk/css/jquery-ui/images/ui-bg_flat_75_ffffff_40x100.png
openhelpdesk/static/openhelpdesk/css/jquery-ui/images/ui-bg_glass_65_ffffff_1x400.png
openhelpdesk/static/openhelpdesk/css/jquery-ui/images/ui-bg_glass_75_dadada_1x400.png
openhelpdesk/static/openhelpdesk/css/jquery-ui/images/ui-bg_glass_75_e6e6e6_1x400.png
