Metadata-Version: 2.0
Name: open-helpdesk
Version: 0.4.4
Summary: Helpdesk app for Django/Mezzanine project
Home-page: https://github.com/simodalla/open-helpdesk
Author: Simone Dalla
Author-email: simodalla@gmail.com
License: BSD
Keywords: open helpdesk
Platform: UNKNOWN
Classifier: Development Status :: 2 - Pre-Alpha
Classifier: Framework :: Django
Classifier: Intended Audience :: Developers
Classifier: License :: OSI Approved :: BSD License
Classifier: Natural Language :: English
Classifier: Programming Language :: Python :: 2
Classifier: Programming Language :: Python :: 2.7
Classifier: Programming Language :: Python :: 3
Classifier: Programming Language :: Python :: 3.3
Classifier: Programming Language :: Python :: 3.4
Requires-Dist: django (>=1.5.10,>=1.6.7,<1.7)
Requires-Dist: mezzanine (>=3.1.0)
Requires-Dist: psycopg2
Requires-Dist: django-model-utils (==2.2)
Requires-Dist: django-braces (==1.4.0)
Requires-Dist: django-autocomplete-light (==2.0.0a18)
